Workbook

Sheet Revenue model
A1: month | C1: 1 | D1: =1+C1 -> 2 | E1: =1+D1 -> 3 | F1: =1+E1 -> 4 | G1: =1+F1 -> 5 | H1: =1+G1 -> 6 | I1: =1+H1 -> 7 | J1: =1+I1 -> 8 | K1: =1+J1 -> 9 | ... AL1: =1+AK1 -> 36
A2: New Customers | C2: 0 | D2: 1 | E2: 2 | F2: 2 | G2: 4 | H2: 4 | I2: 5 | J2: 5 | K2: 6 | L2: 6 | M2: 8 | N2: 8 | O2: 8 | P2: 8 | Q2: 10 | R2: 10 | S2: 10 | T2: 10 | U2: 10 | V2: 10 | W2: 10 | X2: 10 | Y2: 10 | Z2: 10 | AA2: 12 | AB2: 12 | AC2: 12 | AD2: 12 | AE2: 15 | AF2: 15 | AG2: 15 | AH2: 15 | AI2: 20 | AJ2: 20 | AK2: 20 | AL2: 20
A3: New Bookings | C3: =C2*$B14 -> 0 | D3: =D2*$B14 -> 30000 | E3: =E2*$B14 -> 60000 | F3: =F2*$B14 -> 60000 | G3: =G2*$B14 -> 120000 | H3: =H2*$B14 -> 120000 | I3: =I2*$B14 -> 150000 | J3: =J2*$B14 -> 150000 | ... AL3: =AL2*$B14 -> 600000
A5: New MRR | C5: =SUM(C12:C47) -> 0 | D5: =SUM(D12:D47) -> 2500 | E5: =SUM(E12:E47) -> 7500 | F5: =SUM(F12:F47) -> 12500 | G5: =SUM(G12:G47) -> 22500 | H5: =SUM(H12:H47) -> 32500 | I5: =SUM(I12:I47) -> 45000 | J5: =SUM(J12:J47) -> 57500 | ... AL5: =SUM(AL12:AL47) -> 470000
A7: Renewals | C7: 0 | D7: 0 | E7: 0 | F7: 0 | G7: 0 | H7: 0 | I7: 0 | J7: 0 | K7: 0 | L7: 0 | M7: 0 | N7: 0 | O7: =SUM(O49:O73) -> 0 | P7: =SUM(P49:P73) -> 2000 | Q7: =SUM(Q49:Q73) -> 6000 | R7: =SUM(R49:R73) -> 10000 | S7: =SUM(S49:S73) -> 18000 | T7: =SUM(T49:T73) -> 26000 | U7: =SUM(U49:U73) -> 36000 | V7: =SUM(V49:V73) -> 46000 | ... AL7: =SUM(AL49:AL73) -> 352800
A8: Professional Services | C8: =C3*$B$16 -> 0 | D8: =D3*$B$16 -> 9000 | E8: =E3*$B$16 -> 18000 | F8: =F3*$B$16 -> 18000 | G8: =G3*$B$16 -> 36000 | H8: =H3*$B$16 -> 36000 | I8: =I3*$B$16 -> 45000 | J8: =J3*$B$16 -> 45000 | ... AL8: =AL3*$B$16 -> 180000
A9: Total Monthly Revenue | C9: =C5+C7 -> 0 | D9: =D5+D7+D8 -> 11500 | E9: =E5+E7+E8 -> 25500 | F9: =F5+F7+F8 -> 30500 | G9: =G5+G7+G8 -> 58500 | H9: =H5+H7+H8 -> 68500 | I9: =I5+I7+I8 -> 90000 | J9: =J5+J7+J8 -> 102500 | K9: =K5+K7+K8 -> 126500 | ... AL9: =AL5+AL7+AL8 -> 1002800
A10: Total Quarterly Revenue | E10: =SUM(C9:E9) -> 37000 | H10: =SUM(F9:H9) -> 157500 | K10: =SUM(I9:K9) -> 319000 | N10: =SUM(L9:N9) -> 520500 | Q10: =SUM(O9:Q9) -> 739500 | T10: =SUM(R9:T9) -> 984000 | W10: =SUM(U9:W9) -> 1187500 | Z10: =SUM(X9:Z9) -> 1383000 | AC10: =SUM(AA9:AC9) -> 1666700 | AF10: =SUM(AD9:AF9) -> 1986600 | AI10: =SUM(AG9:AI9) -> 2377500 | AL10: =SUM(AJ9:AL9) -> 2870700
A12: MRR table | C12: 0 | D12: 0 | E12: 0 | F12: 0 | G12: 0 | H12: 0 | I12: 0 | J12: 0 | K12: 0 | L12: 0 | M12: 0 | N12: 0
C13: 0 | D13: =$D3/12 -> 2500 | E13: =$D3/12 -> 2500 | F13: =$D3/12 -> 2500 | G13: =$D3/12 -> 2500 | H13: =$D3/12 -> 2500 | I13: =$D3/12 -> 2500 | J13: =$D3/12 -> 2500 | K13: =$D3/12 -> 2500 | ... O13: =$D3/12 -> 2500
A14: Avrg. Unit Price | B14: 30000 | C14: Annual | E14: =$E3/12 -> 5000 | F14: =$E3/12 -> 5000 | G14: =$E3/12 -> 5000 | H14: =$E3/12 -> 5000 | I14: =$E3/12 -> 5000 | J14: =$E3/12 -> 5000 | K14: =$E3/12 -> 5000 | L14: =$E3/12 -> 5000 | ... P14: =$E3/12 -> 5000
A15: Professional Services revenue | F15: =$F3/12 -> 5000 | G15: =$F3/12 -> 5000 | H15: =$F3/12 -> 5000 | I15: =$F3/12 -> 5000 | J15: =$F3/12 -> 5000 | K15: =$F3/12 -> 5000 | L15: =$F3/12 -> 5000 | M15: =$F3/12 -> 5000 | ... Q15: =$F3/12 -> 5000
A16: Ratio to Bookings | B16: 0.3 | G16: =$G3/12 -> 10000 | H16: =$G3/12 -> 10000 | I16: =$G3/12 -> 10000 | J16: =$G3/12 -> 10000 | K16: =$G3/12 -> 10000 | L16: =$G3/12 -> 10000 | M16: =$G3/12 -> 10000 | N16: =$G3/12 -> 10000 | ... R16: =$G3/12 -> 10000
H17: =$H3/12 -> 10000 | I17: =$H3/12 -> 10000 | J17: =$H3/12 -> 10000 | K17: =$H3/12 -> 10000 | L17: =$H3/12 -> 10000 | M17: =$H3/12 -> 10000 | N17: =$H3/12 -> 10000 | O17: =$H3/12 -> 10000 | ... S17: =$H3/12 -> 10000
A18: Only cells in light blue should be edited | I18: =$I3/12 -> 12500 | J18: =$I3/12 -> 12500 | K18: =$I3/12 -> 12500 | L18: =$I3/12 -> 12500 | M18: =$I3/12 -> 12500 | N18: =$I3/12 -> 12500 | O18: =$I3/12 -> 12500 | P18: =$I3/12 -> 12500 | ... T18: =$I3/12 -> 12500
J19: =$J$3/12 -> 12500 | K19: =$J$3/12 -> 12500 | L19: =$J$3/12 -> 12500 | M19: =$J$3/12 -> 12500 | N19: =$J$3/12 -> 12500 | O19: =$J$3/12 -> 12500 | P19: =$J$3/12 -> 12500 | Q19: =$J$3/12 -> 12500 | ... U19: =$J$3/12 -> 12500
A20: March 1, 2025 revision -- Arik Paran -- SCORE Silicon Valley | K20: =$K$3/12 -> 15000 | L20: =$K$3/12 -> 15000 | M20: =$K$3/12 -> 15000 | N20: =$K$3/12 -> 15000 | O20: =$K$3/12 -> 15000 | P20: =$K$3/12 -> 15000 | Q20: =$K$3/12 -> 15000 | R20: =$K$3/12 -> 15000 | ... V20: =$K$3/12 -> 15000
L21: =$L$3/12 -> 15000 | M21: =$L$3/12 -> 15000 | N21: =$L$3/12 -> 15000 | O21: =$L$3/12 -> 15000 | P21: =$L$3/12 -> 15000 | Q21: =$L$3/12 -> 15000 | R21: =$L$3/12 -> 15000 | S21: =$L$3/12 -> 15000 | ... W21: =$L$3/12 -> 15000
M22: =$M$3/12 -> 20000 | N22: =$M$3/12 -> 20000 | O22: =$M$3/12 -> 20000 | P22: =$M$3/12 -> 20000 | Q22: =$M$3/12 -> 20000 | R22: =$M$3/12 -> 20000 | S22: =$M$3/12 -> 20000 | T22: =$M$3/12 -> 20000 | ... X22: =$M$3/12 -> 20000
N23: =$N$3/12 -> 20000 | O23: =$N$3/12 -> 20000 | P23: =$N$3/12 -> 20000 | Q23: =$N$3/12 -> 20000 | R23: =$N$3/12 -> 20000 | S23: =$N$3/12 -> 20000 | T23: =$N$3/12 -> 20000 | U23: =$N$3/12 -> 20000 | ... Y23: =$N$3/12 -> 20000
O24: =$O$3/12 -> 20000 | P24: =$O$3/12 -> 20000 | Q24: =$O$3/12 -> 20000 | R24: =$O$3/12 -> 20000 | S24: =$O$3/12 -> 20000 | T24: =$O$3/12 -> 20000 | U24: =$O$3/12 -> 20000 | V24: =$O$3/12 -> 20000 | ... Z24: =$O$3/12 -> 20000
P25: =$P$3/12 -> 20000 | Q25: =$P$3/12 -> 20000 | R25: =$P$3/12 -> 20000 | S25: =$P$3/12 -> 20000 | T25: =$P$3/12 -> 20000 | U25: =$P$3/12 -> 20000 | V25: =$P$3/12 -> 20000 | W25: =$P$3/12 -> 20000 | ... AA25: =$P$3/12 -> 20000
Q26: =$Q$3/12 -> 25000 | R26: =$Q$3/12 -> 25000 | S26: =$Q$3/12 -> 25000 | T26: =$Q$3/12 -> 25000 | U26: =$Q$3/12 -> 25000 | V26: =$Q$3/12 -> 25000 | W26: =$Q$3/12 -> 25000 | X26: =$Q$3/12 -> 25000 | ... AB26: =$Q$3/12 -> 25000
R27: =$R$3/12 -> 25000 | S27: =$R$3/12 -> 25000 | T27: =$R$3/12 -> 25000 | U27: =$R$3/12 -> 25000 | V27: =$R$3/12 -> 25000 | W27: =$R$3/12 -> 25000 | X27: =$R$3/12 -> 25000 | Y27: =$R$3/12 -> 25000 | ... AC27: =$R$3/12 -> 25000
S28: =$S$3/12 -> 25000 | T28: =$S$3/12 -> 25000 | U28: =$S$3/12 -> 25000 | V28: =$S$3/12 -> 25000 | W28: =$S$3/12 -> 25000 | X28: =$S$3/12 -> 25000 | Y28: =$S$3/12 -> 25000 | Z28: =$S$3/12 -> 25000 | ... AD28: =$S$3/12 -> 25000
T29: =$T$3/12 -> 25000 | U29: =$T$3/12 -> 25000 | V29: =$T$3/12 -> 25000 | W29: =$T$3/12 -> 25000 | X29: =$T$3/12 -> 25000 | Y29: =$T$3/12 -> 25000 | Z29: =$T$3/12 -> 25000 | AA29: =$T$3/12 -> 25000 | ... AE29: =$T$3/12 -> 25000
U30: =$U$3/12 -> 25000 | V30: =$U$3/12 -> 25000 | W30: =$U$3/12 -> 25000 | X30: =$U$3/12 -> 25000 | Y30: =$U$3/12 -> 25000 | Z30: =$U$3/12 -> 25000 | AA30: =$U$3/12 -> 25000 | AB30: =$U$3/12 -> 25000 | ... AF30: =$U$3/12 -> 25000
V31: =$V$3/12 -> 25000 | W31: =$V$3/12 -> 25000 | X31: =$V$3/12 -> 25000 | Y31: =$V$3/12 -> 25000 | Z31: =$V$3/12 -> 25000 | AA31: =$V$3/12 -> 25000 | AB31: =$V$3/12 -> 25000 | AC31: =$V$3/12 -> 25000 | ... AG31: =$V$3/12 -> 25000
W32: =$W$3/12 -> 25000 | X32: =$W$3/12 -> 25000 | Y32: =$W$3/12 -> 25000 | Z32: =$W$3/12 -> 25000 | AA32: =$W$3/12 -> 25000 | AB32: =$W$3/12 -> 25000 | AC32: =$W$3/12 -> 25000 | AD32: =$W$3/12 -> 25000 | ... AH32: =$W$3/12 -> 25000
X33: =$X$3/12 -> 25000 | Y33: =$X$3/12 -> 25000 | Z33: =$X$3/12 -> 25000 | AA33: =$X$3/12 -> 25000 | AB33: =$X$3/12 -> 25000 | AC33: =$X$3/12 -> 25000 | AD33: =$X$3/12 -> 25000 | AE33: =$X$3/12 -> 25000 | ... AI33: =$X$3/12 -> 25000
Y34: =$Y$3/12 -> 25000 | Z34: =$Y$3/12 -> 25000 | AA34: =$Y$3/12 -> 25000 | AB34: =$Y$3/12 -> 25000 | AC34: =$Y$3/12 -> 25000 | AD34: =$Y$3/12 -> 25000 | AE34: =$Y$3/12 -> 25000 | AF34: =$Y$3/12 -> 25000 | ... AJ34: =$Y$3/12 -> 25000
Z35: =$Z$3/12 -> 25000 | AA35: =$Z$3/12 -> 25000 | AB35: =$Z$3/12 -> 25000 | AC35: =$Z$3/12 -> 25000 | AD35: =$Z$3/12 -> 25000 | AE35: =$Z$3/12 -> 25000 | AF35: =$Z$3/12 -> 25000 | AG35: =$Z$3/12 -> 25000 | ... AK35: =$Z$3/12 -> 25000
AA36: =$AA$3/12 -> 30000 | AB36: =$AA$3/12 -> 30000 | AC36: =$AA$3/12 -> 30000 | AD36: =$AA$3/12 -> 30000 | AE36: =$AA$3/12 -> 30000 | AF36: =$AA$3/12 -> 30000 | AG36: =$AA$3/12 -> 30000 | AH36: =$AA$3/12 -> 30000 | ... AL36: =$AA$3/12 -> 30000
AB37: =$AB$3/12 -> 30000 | AC37: =$AB$3/12 -> 30000 | AD37: =$AB$3/12 -> 30000 | AE37: =$AB$3/12 -> 30000 | AF37: =$AB$3/12 -> 30000 | AG37: =$AB$3/12 -> 30000 | AH37: =$AB$3/12 -> 30000 | AI37: =$AB$3/12 -> 30000 | ... AL37: =$AB$3/12 -> 30000
AC38: =$AC$3/12 -> 30000 | AD38: =$AC$3/12 -> 30000 | AE38: =$AC$3/12 -> 30000 | AF38: =$AC$3/12 -> 30000 | AG38: =$AC$3/12 -> 30000 | AH38: =$AC$3/12 -> 30000 | AI38: =$AC$3/12 -> 30000 | AJ38: =$AC$3/12 -> 30000 | ... AL38: =$AC$3/12 -> 30000
AD39: =$AD$3/12 -> 30000 | AE39: =$AD$3/12 -> 30000 | AF39: =$AD$3/12 -> 30000 | AG39: =$AD$3/12 -> 30000 | AH39: =$AD$3/12 -> 30000 | AI39: =$AD$3/12 -> 30000 | AJ39: =$AD$3/12 -> 30000 | AK39: =$AD$3/12 -> 30000 | AL39: =$AD$3/12 -> 30000
AE40: =$AE$3/12 -> 37500 | AF40: =$AE$3/12 -> 37500 | AG40: =$AE$3/12 -> 37500 | AH40: =$AE$3/12 -> 37500 | AI40: =$AE$3/12 -> 37500 | AJ40: =$AE$3/12 -> 37500 | AK40: =$AE$3/12 -> 37500 | AL40: =$AE$3/12 -> 37500
AF41: =$AF$3/12 -> 37500 | AG41: =$AF$3/12 -> 37500 | AH41: =$AF$3/12 -> 37500 | AI41: =$AF$3/12 -> 37500 | AJ41: =$AF$3/12 -> 37500 | AK41: =$AF$3/12 -> 37500 | AL41: =$AF$3/12 -> 37500
AG42: =$AG$3/12 -> 37500 | AH42: =$AG$3/12 -> 37500 | AI42: =$AG$3/12 -> 37500 | AJ42: =$AG$3/12 -> 37500 | AK42: =$AG$3/12 -> 37500 | AL42: =$AG$3/12 -> 37500
AH43: =$AH$3/12 -> 37500 | AI43: =$AG$3/12 -> 37500 | AJ43: =$AG$3/12 -> 37500 | AK43: =$AG$3/12 -> 37500 | AL43: =$AG$3/12 -> 37500
AI44: =$AI$3/12 -> 50000 | AJ44: =$AI$3/12 -> 50000 | AK44: =$AI$3/12 -> 50000 | AL44: =$AI$3/12 -> 50000
AJ45: =$AJ$3/12 -> 50000 | AK45: =$AJ$3/12 -> 50000 | AL45: =$AJ$3/12 -> 50000
AK46: =$AK$3/12 -> 50000 | AL46: =$AK$3/12 -> 50000
AL47: =$AL$3/12 -> 50000
A49: Renewals table | C49: 0.8 | D49: 0.9 | O49: =$C$49*C12 -> 0 | P49: =$C$49*D12 -> 0 | Q49: =$C$49*E12 -> 0 | R49: =$C$49*F12 -> 0 | S49: =$C$49*G12 -> 0 | T49: =$C$49*H12 -> 0 | U49: =$C$49*I12 -> 0 | V49: =$C$49*J12 -> 0 | ... Z49: =$C$49*N12 -> 0 | AA49: =$D$49*O49 -> 0 | AB49: =$D$49*P49 -> 0 | AC49: =$D$49*Q49 -> 0 | AD49: =$D$49*R49 -> 0 | AE49: =$D$49*S49 -> 0 | AF49: =$D$49*T49 -> 0 | AG49: =$D$49*U49 -> 0 | AH49: =$D$49*V49 -> 0 | ... AL49: =$D$49*Z49 -> 0
C50: 2nd year | D50: 3rd year | O50: =$C$49*C13 -> 0 | P50: =$C$49*D13 -> 2000 | Q50: =$C$49*E13 -> 2000 | R50: =$C$49*F13 -> 2000 | S50: =$C$49*G13 -> 2000 | T50: =$C$49*H13 -> 2000 | U50: =$C$49*I13 -> 2000 | V50: =$C$49*J13 -> 2000 | ... AA50: =$C$49*O13 -> 2000 | AB50: =$D$49*P50 -> 1800 | AC50: =$D$49*Q50 -> 1800 | AD50: =$D$49*R50 -> 1800 | AE50: =$D$49*S50 -> 1800 | AF50: =$D$49*T50 -> 1800 | AG50: =$D$49*U50 -> 1800 | AH50: =$D$49*V50 -> 1800 | AI50: =$D$49*W50 -> 1800 | ... AL50: =$D$49*Z50 -> 1800
O51: 0 | P51: =$C$49*D14 -> 0 | Q51: =$C$49*E14 -> 4000 | R51: =$C$49*F14 -> 4000 | S51: =$C$49*G14 -> 4000 | T51: =$C$49*H14 -> 4000 | U51: =$C$49*I14 -> 4000 | V51: =$C$49*J14 -> 4000 | W51: =$C$49*K14 -> 4000 | ... AB51: =$C$49*P14 -> 4000 | AC51: =$D$49*Q51 -> 3600 | AD51: =$D$49*R51 -> 3600 | AE51: =$D$49*S51 -> 3600 | AF51: =$D$49*T51 -> 3600 | AG51: =$D$49*U51 -> 3600 | AH51: =$D$49*V51 -> 3600 | AI51: =$D$49*W51 -> 3600 | AJ51: =$D$49*X51 -> 3600 | ... AL51: =$D$49*Z51 -> 3600
O52: =$C$49*C15 -> 0 | P52: =$C$49*D15 -> 0 | Q52: =$C$49*E15 -> 0 | R52: =$C$49*F15 -> 4000 | S52: =$C$49*G15 -> 4000 | T52: =$C$49*H15 -> 4000 | U52: =$C$49*I15 -> 4000 | V52: =$C$49*J15 -> 4000 | ... AC52: =$C$49*Q15 -> 4000 | AD52: =$D$49*R52 -> 3600 | AE52: =$D$49*S52 -> 3600 | AF52: =$D$49*T52 -> 3600 | AG52: =$D$49*U52 -> 3600 | AH52: =$D$49*V52 -> 3600 | AI52: =$D$49*W52 -> 3600 | AJ52: =$D$49*X52 -> 3600 | AK52: =$D$49*Y52 -> 3600 | AL52: =$D$49*Z52 -> 3600
O53: =$C$49*C16 -> 0 | P53: =$C$49*D16 -> 0 | Q53: =$C$49*E16 -> 0 | R53: =$C$49*F16 -> 0 | S53: =$C$49*G16 -> 8000 | T53: =$C$49*H16 -> 8000 | U53: =$C$49*I16 -> 8000 | V53: =$C$49*J16 -> 8000 | ... AD53: =$C$49*R16 -> 8000 | AE53: =$D$49*S53 -> 7200 | AF53: =$D$49*T53 -> 7200 | AG53: =$D$49*U53 -> 7200 | AH53: =$D$49*V53 -> 7200 | AI53: =$D$49*W53 -> 7200 | AJ53: =$D$49*X53 -> 7200 | AK53: =$D$49*Y53 -> 7200 | AL53: =$D$49*Z53 -> 7200
O54: =$C$49*C17 -> 0 | P54: =$C$49*D17 -> 0 | Q54: =$C$49*E17 -> 0 | R54: =$C$49*F17 -> 0 | S54: =$C$49*G17 -> 0 | T54: =$C$49*H17 -> 8000 | U54: =$C$49*I17 -> 8000 | V54: =$C$49*J17 -> 8000 | ... AE54: =$C$49*S17 -> 8000 | AF54: =$D$49*T54 -> 7200 | AG54: =$D$49*U54 -> 7200 | AH54: =$D$49*V54 -> 7200 | AI54: =$D$49*W54 -> 7200 | AJ54: =$D$49*X54 -> 7200 | AK54: =$D$49*Y54 -> 7200 | AL54: =$D$49*Z54 -> 7200
O55: =$C$49*C18 -> 0 | P55: =$C$49*D18 -> 0 | Q55: =$C$49*E18 -> 0 | R55: =$C$49*F18 -> 0 | S55: =$C$49*G18 -> 0 | T55: =$C$49*H18 -> 0 | U55: =$C$49*I18 -> 10000 | V55: =$C$49*J18 -> 10000 | ... AF55: =$C$49*T18 -> 10000 | AG55: =$D$49*U55 -> 9000 | AH55: =$D$49*V55 -> 9000 | AI55: =$D$49*W55 -> 9000 | AJ55: =$D$49*X55 -> 9000 | AK55: =$D$49*Y55 -> 9000 | AL55: =$D$49*Z55 -> 9000
O56: =$C$49*C19 -> 0 | P56: =$C$49*D19 -> 0 | Q56: =$C$49*E19 -> 0 | R56: =$C$49*F19 -> 0 | S56: =$C$49*G19 -> 0 | T56: =$C$49*H19 -> 0 | U56: =$C$49*I19 -> 0 | V56: =$C$49*J19 -> 10000 | ... AG56: =$C$49*U19 -> 10000 | AH56: =$D$49*V56 -> 9000 | AI56: =$D$49*W56 -> 9000 | AJ56: =$D$49*X56 -> 9000 | AK56: =$D$49*Y56 -> 9000 | AL56: =$D$49*Z56 -> 9000
O57: =$C$49*C20 -> 0 | P57: =$C$49*D20 -> 0 | Q57: =$C$49*E20 -> 0 | R57: =$C$49*F20 -> 0 | S57: =$C$49*G20 -> 0 | T57: =$C$49*H20 -> 0 | U57: =$C$49*I20 -> 0 | V57: =$C$49*J20 -> 0 | ... AH57: =$C$49*V20 -> 12000 | AI57: =$D$49*W57 -> 10800 | AJ57: =$D$49*X57 -> 10800 | AK57: =$D$49*Y57 -> 10800 | AL57: =$D$49*Z57 -> 10800
O58: =$C$49*C21 -> 0 | P58: =$C$49*D21 -> 0 | Q58: =$C$49*E21 -> 0 | R58: =$C$49*F21 -> 0 | S58: =$C$49*G21 -> 0 | T58: =$C$49*H21 -> 0 | U58: =$C$49*I21 -> 0 | V58: =$C$49*J21 -> 0 | ... AI58: =$C$49*W21 -> 12000 | AJ58: =$D$49*X58 -> 10800 | AK58: =$D$49*Y58 -> 10800 | AL58: =$D$49*Z58 -> 10800
O59: =$C$49*C22 -> 0 | P59: =$C$49*D22 -> 0 | Q59: =$C$49*E22 -> 0 | R59: =$C$49*F22 -> 0 | S59: =$C$49*G22 -> 0 | T59: =$C$49*H22 -> 0 | U59: =$C$49*I22 -> 0 | V59: =$C$49*J22 -> 0 | ... AJ59: =$C$49*X22 -> 16000 | AK59: =$D$49*Y59 -> 14400 | AL59: =$D$49*Z59 -> 14400
O60: =$C$49*C23 -> 0 | P60: =$C$49*D23 -> 0 | Q60: =$C$49*E23 -> 0 | R60: =$C$49*F23 -> 0 | S60: =$C$49*G23 -> 0 | T60: =$C$49*H23 -> 0 | U60: =$C$49*I23 -> 0 | V60: =$C$49*J23 -> 0 | ... AK60: =$C$49*Y23 -> 16000 | AL60: =$D$49*Z60 -> 14400
O61: =$C$49*C24 -> 0 | P61: =$C$49*D24 -> 0 | Q61: =$C$49*E24 -> 0 | R61: =$C$49*F24 -> 0 | S61: =$C$49*G24 -> 0 | T61: =$C$49*H24 -> 0 | U61: =$C$49*I24 -> 0 | V61: =$C$49*J24 -> 0 | ... Z61: =$C$49*N24 -> 0 | AA61: =$D$49*O24 -> 18000 | AB61: =$D$49*P24 -> 18000 | AC61: =$D$49*Q24 -> 18000 | AD61: =$D$49*R24 -> 18000 | AE61: =$D$49*S24 -> 18000 | AF61: =$D$49*T24 -> 18000 | AG61: =$D$49*U24 -> 18000 | AH61: =$D$49*V24 -> 18000 | ... AL61: =$D$49*Z24 -> 18000
O62: =$C$49*C25 -> 0 | P62: =$C$49*D25 -> 0 | Q62: =$C$49*E25 -> 0 | R62: =$C$49*F25 -> 0 | S62: =$C$49*G25 -> 0 | T62: =$C$49*H25 -> 0 | U62: =$C$49*I25 -> 0 | V62: =$C$49*J25 -> 0 | ... Z62: =$C$49*N25 -> 0 | AA62: =$D$49*O25 -> 0 | AB62: =$D$49*P25 -> 18000 | AC62: =$D$49*Q25 -> 18000 | AD62: =$D$49*R25 -> 18000 | AE62: =$D$49*S25 -> 18000 | AF62: =$D$49*T25 -> 18000 | AG62: =$D$49*U25 -> 18000 | AH62: =$D$49*V25 -> 18000 | ... AL62: =$D$49*Z25 -> 18000
O63: =$C$49*C26 -> 0 | P63: =$C$49*D26 -> 0 | Q63: =$C$49*E26 -> 0 | R63: =$C$49*F26 -> 0 | S63: =$C$49*G26 -> 0 | T63: =$C$49*H26 -> 0 | U63: =$C$49*I26 -> 0 | V63: =$C$49*J26 -> 0 | ... Z63: =$C$49*N26 -> 0 | AA63: =$D$49*O26 -> 0 | AB63: =$D$49*P26 -> 0 | AC63: =$D$49*Q26 -> 22500 | AD63: =$D$49*R26 -> 22500 | AE63: =$D$49*S26 -> 22500 | AF63: =$D$49*T26 -> 22500 | AG63: =$D$49*U26 -> 22500 | AH63: =$D$49*V26 -> 22500 | ... AL63: =$D$49*Z26 -> 22500
O64: =$C$49*C27 -> 0 | P64: =$C$49*D27 -> 0 | Q64: =$C$49*E27 -> 0 | R64: =$C$49*F27 -> 0 | S64: =$C$49*G27 -> 0 | T64: =$C$49*H27 -> 0 | U64: =$C$49*I27 -> 0 | V64: =$C$49*J27 -> 0 | ... Z64: =$C$49*N27 -> 0 | AA64: =$D$49*O27 -> 0 | AB64: =$D$49*P27 -> 0 | AC64: =$D$49*Q27 -> 0 | AD64: =$D$49*R27 -> 22500 | AE64: =$D$49*S27 -> 22500 | AF64: =$D$49*T27 -> 22500 | AG64: =$D$49*U27 -> 22500 | AH64: =$D$49*V27 -> 22500 | ... AL64: =$D$49*Z27 -> 22500
O65: =$C$49*C28 -> 0 | P65: =$C$49*D28 -> 0 | Q65: =$C$49*E28 -> 0 | R65: =$C$49*F28 -> 0 | S65: =$C$49*G28 -> 0 | T65: =$C$49*H28 -> 0 | U65: =$C$49*I28 -> 0 | V65: =$C$49*J28 -> 0 | ... Z65: =$C$49*N28 -> 0 | AA65: =$D$49*O28 -> 0 | AB65: =$D$49*P28 -> 0 | AC65: =$D$49*Q28 -> 0 | AD65: =$D$49*R28 -> 0 | AE65: =$D$49*S28 -> 22500 | AF65: =$D$49*T28 -> 22500 | AG65: =$D$49*U28 -> 22500 | AH65: =$D$49*V28 -> 22500 | ... AL65: =$D$49*Z28 -> 22500
O66: =$C$49*C29 -> 0 | P66: =$C$49*D29 -> 0 | Q66: =$C$49*E29 -> 0 | R66: =$C$49*F29 -> 0 | S66: =$C$49*G29 -> 0 | T66: =$C$49*H29 -> 0 | U66: =$C$49*I29 -> 0 | V66: =$C$49*J29 -> 0 | ... Z66: =$C$49*N29 -> 0 | AA66: =$D$49*O29 -> 0 | AB66: =$D$49*P29 -> 0 | AC66: =$D$49*Q29 -> 0 | AD66: =$D$49*R29 -> 0 | AE66: =$D$49*S29 -> 0 | AF66: =$D$49*T29 -> 22500 | AG66: =$D$49*U29 -> 22500 | AH66: =$D$49*V29 -> 22500 | ... AL66: =$D$49*Z29 -> 22500
O67: =$C$49*C30 -> 0 | P67: =$C$49*D30 -> 0 | Q67: =$C$49*E30 -> 0 | R67: =$C$49*F30 -> 0 | S67: =$C$49*G30 -> 0 | T67: =$C$49*H30 -> 0 | U67: =$C$49*I30 -> 0 | V67: =$C$49*J30 -> 0 | ... Z67: =$C$49*N30 -> 0 | AA67: =$D$49*O30 -> 0 | AB67: =$D$49*P30 -> 0 | AC67: =$D$49*Q30 -> 0 | AD67: =$D$49*R30 -> 0 | AE67: =$D$49*S30 -> 0 | AF67: =$D$49*T30 -> 0 | AG67: =$D$49*U30 -> 22500 | AH67: =$D$49*V30 -> 22500 | ... AL67: =$D$49*Z30 -> 22500
O68: =$C$49*C31 -> 0 | P68: =$C$49*D31 -> 0 | Q68: =$C$49*E31 -> 0 | R68: =$C$49*F31 -> 0 | S68: =$C$49*G31 -> 0 | T68: =$C$49*H31 -> 0 | U68: =$C$49*I31 -> 0 | V68: =$C$49*J31 -> 0 | ... Z68: =$C$49*N31 -> 0 | AA68: =$D$49*O31 -> 0 | AB68: =$D$49*P31 -> 0 | AC68: =$D$49*Q31 -> 0 | AD68: =$D$49*R31 -> 0 | AE68: =$D$49*S31 -> 0 | AF68: =$D$49*T31 -> 0 | AG68: =$D$49*U31 -> 0 | AH68: =$D$49*V31 -> 22500 | ... AL68: =$D$49*Z31 -> 22500
O69: =$C$49*C32 -> 0 | P69: =$C$49*D32 -> 0 | Q69: =$C$49*E32 -> 0 | R69: =$C$49*F32 -> 0 | S69: =$C$49*G32 -> 0 | T69: =$C$49*H32 -> 0 | U69: =$C$49*I32 -> 0 | V69: =$C$49*J32 -> 0 | ... Z69: =$C$49*N32 -> 0 | AA69: =$D$49*O32 -> 0 | AB69: =$D$49*P32 -> 0 | AC69: =$D$49*Q32 -> 0 | AD69: =$D$49*R32 -> 0 | AE69: =$D$49*S32 -> 0 | AF69: =$D$49*T32 -> 0 | AG69: =$D$49*U32 -> 0 | AH69: =$D$49*V32 -> 0 | ... AL69: =$D$49*Z32 -> 22500
O70: =$C$49*C33 -> 0 | P70: =$C$49*D33 -> 0 | Q70: =$C$49*E33 -> 0 | R70: =$C$49*F33 -> 0 | S70: =$C$49*G33 -> 0 | T70: =$C$49*H33 -> 0 | U70: =$C$49*I33 -> 0 | V70: =$C$49*J33 -> 0 | ... Z70: =$C$49*N33 -> 0 | AA70: =$D$49*O33 -> 0 | AB70: =$D$49*P33 -> 0 | AC70: =$D$49*Q33 -> 0 | AD70: =$D$49*R33 -> 0 | AE70: =$D$49*S33 -> 0 | AF70: =$D$49*T33 -> 0 | AG70: =$D$49*U33 -> 0 | AH70: =$D$49*V33 -> 0 | ... AL70: =$D$49*Z33 -> 22500
O71: =$C$49*C34 -> 0 | P71: =$C$49*D34 -> 0 | Q71: =$C$49*E34 -> 0 | R71: =$C$49*F34 -> 0 | S71: =$C$49*G34 -> 0 | T71: =$C$49*H34 -> 0 | U71: =$C$49*I34 -> 0 | V71: =$C$49*J34 -> 0 | ... Z71: =$C$49*N34 -> 0 | AA71: =$D$49*O34 -> 0 | AB71: =$D$49*P34 -> 0 | AC71: =$D$49*Q34 -> 0 | AD71: =$D$49*R34 -> 0 | AE71: =$D$49*S34 -> 0 | AF71: =$D$49*T34 -> 0 | AG71: =$D$49*U34 -> 0 | AH71: =$D$49*V34 -> 0 | ... AL71: =$D$49*Z34 -> 22500
O72: =$C$49*C35 -> 0 | P72: =$C$49*D35 -> 0 | Q72: =$C$49*E35 -> 0 | R72: =$C$49*F35 -> 0 | S72: =$C$49*G35 -> 0 | T72: =$C$49*H35 -> 0 | U72: =$C$49*I35 -> 0 | V72: =$C$49*J35 -> 0 | ... Z72: =$C$49*N35 -> 0 | AA72: =$D$49*O35 -> 0 | AB72: =$D$49*P35 -> 0 | AC72: =$D$49*Q35 -> 0 | AD72: =$D$49*R35 -> 0 | AE72: =$D$49*S35 -> 0 | AF72: =$D$49*T35 -> 0 | AG72: =$D$49*U35 -> 0 | AH72: =$D$49*V35 -> 0 | ... AL72: =$D$49*Z35 -> 22500
O73: =$C$49*C36 -> 0 | P73: =$C$49*D36 -> 0 | Q73: =$C$49*E36 -> 0 | R73: =$C$49*F36 -> 0 | S73: =$C$49*G36 -> 0 | T73: =$C$49*H36 -> 0 | U73: =$C$49*I36 -> 0 | V73: =$C$49*J36 -> 0 | ... Z73: =$C$49*N36 -> 0 | AA73: =$D$49*O36 -> 0 | AB73: =$D$49*P36 -> 0 | AC73: =$D$49*Q36 -> 0 | AD73: =$D$49*R36 -> 0 | AE73: =$D$49*S36 -> 0 | AF73: =$D$49*T36 -> 0 | AG73: =$D$49*U36 -> 0 | AH73: =$D$49*V36 -> 0 | ... AL73: =$D$49*Z36 -> 0

Sheet P&L
A1: Month | B1: 1 | C1: =B1+1 -> 2 | D1: =C1+1 -> 3 | E1: =D1+1 -> 4 | F1: =E1+1 -> 5 | G1: =F1+1 -> 6 | H1: =G1+1 -> 7 | I1: =H1+1 -> 8 | J1: =I1+1 -> 9 | ... AK1: =AJ1+1 -> 36
A2: New Customers | B2: ='Revenue model'!C2 -> 0 | C2: ='Revenue model'!D2 -> 1 | D2: ='Revenue model'!E2 -> 2 | E2: ='Revenue model'!F2 -> 2 | F2: ='Revenue model'!G2 -> 4 | G2: ='Revenue model'!H2 -> 4 | H2: ='Revenue model'!I2 -> 5 | I2: ='Revenue model'!J2 -> 5 | ... AK2: ='Revenue model'!AL2 -> 20
A3: Total Customers | B3: =B2 -> 0 | C3: =C2+B3 -> 1 | D3: =D2+C3 -> 3 | E3: =E2+D3 -> 5 | F3: =F2+E3 -> 9 | G3: =G2+F3 -> 13 | H3: =H2+G3 -> 18 | I3: =I2+H3 -> 23 | J3: =J2+I3 -> 29 | ... AK3: =AK2+AJ3 -> 355
A4: New Bookings | B4: ='Revenue model'!C3 -> 0 | C4: ='Revenue model'!D3 -> 30000 | D4: ='Revenue model'!E3 -> 60000 | E4: ='Revenue model'!F3 -> 60000 | F4: ='Revenue model'!G3 -> 120000 | G4: ='Revenue model'!H3 -> 120000 | H4: ='Revenue model'!I3 -> 150000 | I4: ='Revenue model'!J3 -> 150000 | ... AK4: ='Revenue model'!AL3 -> 600000
A5: License Revenue | B5: ='Revenue model'!C9-'Revenue model'!C8 -> 0 | C5: ='Revenue model'!D9-'Revenue model'!D8 -> 2500 | D5: ='Revenue model'!E9-'Revenue model'!E8 -> 7500 | E5: ='Revenue model'!F9-'Revenue model'!F8 -> 12500 | F5: ='Revenue model'!G9-'Revenue model'!G8 -> 22500 | G5: ='Revenue model'!H9-'Revenue model'!H8 -> 32500 | H5: ='Revenue model'!I9-'Revenue model'!I8 -> 45000 | I5: ='Revenue model'!J9-'Revenue model'!J8 -> 57500 | ... AK5: ='Revenue model'!AL9-'Revenue model'!AL8 -> 822800
A6: PS Revenue | B6: ='Revenue model'!C8 -> 0 | C6: ='Revenue model'!D8 -> 9000 | D6: ='Revenue model'!E8 -> 18000 | E6: ='Revenue model'!F8 -> 18000 | F6: ='Revenue model'!G8 -> 36000 | G6: ='Revenue model'!H8 -> 36000 | H6: ='Revenue model'!I8 -> 45000 | I6: ='Revenue model'!J8 -> 45000 | ... AK6: ='Revenue model'!AL8 -> 180000
A7: Marking Expenses | B7: =$B35*C4 -> 4500 | C7: =$B35*D4 -> 9000 | D7: =$B35*E4 -> 9000 | E7: =$B35*F4 -> 18000 | F7: =$B35*G4 -> 18000 | G7: =$B35*H4 -> 22500 | H7: =$B35*I4 -> 22500 | I7: =$B35*J4 -> 27000 | ... AJ7: =$B35*AK4 -> 90000 | AK7: =$B35*AK4 -> 90000
A8: Sales Commission | B8: =$B33*B4 -> 0 | C8: =$B33*C4 -> 4500 | D8: =$B33*D4 -> 9000 | E8: =$B33*E4 -> 9000 | F8: =$B33*F4 -> 18000 | G8: =$B33*G4 -> 18000 | H8: =$B33*H4 -> 22500 | I8: =$B33*I4 -> 22500 | ... AK8: =$B33*AK4 -> 90000
A10: Sales people | B10: =D4*$B43/$B32 -> 0.45 | C10: =E4*$B43/$B32 -> 0.45 | D10: =F4*$B43/$B32 -> 0.9 | E10: =G4*$B43/$B32 -> 0.9 | F10: =H4*$B43/$B32 -> 1.125 | G10: =I4*$B43/$B32 -> 1.125 | H10: =J4*$B43/$B32 -> 1.35 | I10: =K4*$B43/$B32 -> 1.35 | ... AI10: =AK4*$B43/$B32 -> 4.5 | AJ10: =AI10+0.5 -> 5 | AK10: =AJ10+0.5 -> 5.5
A11: Sales OPS | B11: =B10*$B34 -> 0.045 | C11: =C10*$B34 -> 0.045 | D11: =D10*$B34 -> 0.09 | E11: =E10*$B34 -> 0.09 | F11: =F10*$B34 -> 0.1125 | G11: =G10*$B34 -> 0.1125 | H11: =H10*$B34 -> 0.135 | I11: =I10*$B34 -> 0.135 | ... AK11: =AK10*$B34 -> 0.55
A12: Customer Success staff | B12: =$B29*$B41*B5/$B26 -> 0 | C12: =$B29*$B41*C5/$B26 -> 0.015 | D12: =$B29*$B41*D5/$B26 -> 0.045 | E12: =$B29*$B41*E5/$B26 -> 0.075 | F12: =$B29*$B41*F5/$B26 -> 0.135 | G12: =$B29*$B41*G5/$B26 -> 0.195 | H12: =$B29*$B41*H5/$B26 -> 0.27 | I12: =$B29*$B41*I5/$B26 -> 0.345 | ... AK12: =$B29*$B41*AK5/$B26 -> 4.9368
A13: Support Staff | B13: =$B30*$B40*B5/$B26 -> 0 | C13: =$B30*$B40*C5/$B26 -> 0.0025 | D13: =$B30*$B40*D5/$B26 -> 0.0075 | E13: =$B30*$B40*E5/$B26 -> 0.0125 | F13: =$B30*$B40*F5/$B26 -> 0.0225 | G13: =$B30*$B40*G5/$B26 -> 0.0325 | H13: =$B30*$B40*H5/$B26 -> 0.045 | I13: =$B30*$B40*I5/$B26 -> 0.0575 | ... AK13: =$B30*$B40*AK5/$B26 -> 0.8228
A14: PS staff
A16: Headcount
A17: Sales | B17: =1+ROUNDUP(B10+B11,0) -> 2 | C17: =1+ROUNDUP(C10+C11,0) -> 2 | D17: =1+ROUNDUP(D10+D11,0) -> 2 | E17: =1+ROUNDUP(E10+E11,0) -> 2 | F17: =1+ROUNDUP(F10+F11,0) -> 3 | G17: =1+ROUNDUP(G10+G11,0) -> 3 | H17: =1+ROUNDUP(H10+H11,0) -> 3 | I17: =1+ROUNDUP(I10+I11,0) -> 3 | ... AK17: =1+ROUNDUP(AK10+AK11,0) -> 8
A18: Cust. Succ. + Support | B18: =1+ROUNDUP(B12+B13,0) -> 1 | C18: =1+ROUNDUP(C12+C13,0) -> 2 | D18: =1+ROUNDUP(D12+D13,0) -> 2 | E18: =1+ROUNDUP(E12+E13,0) -> 2 | F18: =1+ROUNDUP(F12+F13,0) -> 2 | G18: =1+ROUNDUP(G12+G13,0) -> 2 | H18: =1+ROUNDUP(H12+H13,0) -> 2 | I18: =1+ROUNDUP(I12+I13,0) -> 2 | ... AK18: =1+ROUNDUP(AK12+AK13,0) -> 7
A19: Professional Services | B19: =1+ROUNDUP(B6*$B42/$B31,0) -> 1 | C19: =1+ROUNDUP(C6*$B42/$B31,0) -> 2 | D19: =1+ROUNDUP(D6*$B42/$B31,0) -> 2 | E19: =1+ROUNDUP(E6*$B42/$B31,0) -> 2 | F19: =1+ROUNDUP(F6*$B42/$B31,0) -> 3 | G19: =1+ROUNDUP(G6*$B42/$B31,0) -> 3 | H19: =1+ROUNDUP(H6*$B42/$B31,0) -> 3 | I19: =1+ROUNDUP(I6*$B42/$B31,0) -> 3 | ... AK19: =1+ROUNDUP(AK6*$B42/$B31,0) -> 9
A20: Marketing | B20: 2 | C20: 2 | D20: 2 | E20: 2 | F20: 2 | G20: 2 | H20: 2 | I20: 2 | J20: 2 | K20: 2 | L20: 2 | M20: 2 | N20: 3 | O20: 3 | P20: 3 | Q20: 3 | R20: 3 | S20: 3 | T20: 3 | U20: 3 | V20: 3 | W20: 3 | X20: 3 | Y20: 3 | Z20: 3 | AA20: 3 | AB20: 3 | AC20: 3 | AD20: 3 | AE20: 3 | AF20: 3 | AG20: 3 | AH20: 3 | AI20: 3 | AJ20: 3 | AK20: 3
A21: Engineering | B21: 3 | C21: 3 | D21: 3 | E21: 3 | F21: 3 | G21: 3 | H21: 3 | I21: 3 | J21: 3 | K21: 3 | L21: 3 | M21: 3 | N21: 5 | O21: 5 | P21: 5 | Q21: 5 | R21: 5 | S21: 5 | T21: 5 | U21: 5 | V21: 5 | W21: 5 | X21: 5 | Y21: 5 | Z21: 5 | AA21: 5 | AB21: 5 | AC21: 5 | AD21: 5 | AE21: 5 | AF21: 5 | AG21: 5 | AH21: 5 | AI21: 5 | AJ21: 5 | AK21: 5
A22: G&A | B22: 2 | C22: 2 | D22: 2 | E22: 2 | F22: 2 | G22: 2 | H22: 3 | I22: 3 | J22: 3 | K22: 3 | L22: 3 | M22: 3 | N22: 3 | O22: 3 | P22: 3 | Q22: 3 | R22: 3 | S22: 3 | T22: 4 | U22: 4 | V22: 4 | W22: 4 | X22: 4 | Y22: 4 | Z22: 4 | AA22: 4 | AB22: 4 | AC22: 4 | AD22: 4 | AE22: 4 | AF22: 5 | AG22: 5 | AH22: 5 | AI22: 5 | AJ22: 5 | AK22: 5
A23: Total HC | B23: =SUM(B17:B22) -> 11 | C23: =SUM(C17:C22) -> 13 | D23: =SUM(D17:D22) -> 13 | E23: =SUM(E17:E22) -> 13 | F23: =SUM(F17:F22) -> 15 | G23: =SUM(G17:G22) -> 15 | H23: =SUM(H17:H22) -> 16 | I23: =SUM(I17:I22) -> 16 | ... AK23: =SUM(AK17:AK22) -> 37
A25: Avrg Price | B25: ='Revenue model'!B14 -> 30000 | C25: from Revenue Model
A26: Avrg HC cost | B26: 10000 | C26: Monthly | G26: You must edit the marketing, engineering, and G&A headcount numbers above
A27: G&A overhead | B27: 0.25 | C27: of G&A headcount
A28: AI Agents cost (avrg) | B28: 10000 | C28: Per headcount | E28: Adjust!
A29: Customer Success Ratio | B29: 0.2 | C29: of Revenue (cost of CS) | G29: Only cells in light blue should be edited
A30: Support Ratio | B30: 0.05 | C30: of Revenue (cost of support)
A31: Pro. Serv. capacity | B31: 18000 | C31: Monthly revenue capacity per person
A32: Sales qouta monthly | B32: 100000 | C32: of Bookings | D32: 6 months out | G32: March 1, 2025 revision -- Arik Paran -- SCORE Silicon Valley | L32: Updated with new AI effects
A33: Sales commission Rate | B33: 0.15 | C33: of Bookings
A34: Sales/OPS ratio | B34: 0.1 | C34: Sales OPS HC ratio to Sales people HC
A35: Markteting Cost Ratio | B35: 0.15 | C35: of Bookings | D35: 3 months out
A37: Engineering AI factor | B37: 0.5 | C37: Remaining effort with AI leverage (manual) | G37: Review your headcount and adjust accoring to technology use to Leverage AI agents
A38: G&A AI factor | B38: 0.75 | C38: Remaining effort with AI leverage (manual) | G38: Review your headcount and adjust accoring to technology use to Leverage AI agents
A39: Marketing AI factor | B39: 0.5 | C39: Remaining effort with AI leverage (manual) | G39: Review your headcount and adjust accoring to technology use to Leverage AI agents
A40: Customer Support AI factor | B40: 0.2 | C40: Remaining effort with AI leverage (auto) | G40: Factor is already within the functions in the tables above
A41: Customer Success AI factor | B41: 0.3 | C41: Remaining effort with AI leverage (auto) | G41: Factor is already within the functions in the tables above
A42: Prof. Servicves AI factor | B42: 0.75 | C42: Remaining effort with AI leverage (auto) | G42: Factor is already within the functions in the tables above
A43: Sales AI factor | B43: 0.75 | C43: Remaining effort with AI leverage (auto) | G43: Factor is already within the functions in the tables above
A46: P&L
B47: =B1 -> 1 | C47: =C1 -> 2 | D47: =D1 -> 3 | E47: =E1 -> 4 | F47: =F1 -> 5 | G47: =G1 -> 6 | H47: =H1 -> 7 | I47: =I1 -> 8 | ... AK47: =AK1 -> 36
A48: Revenue | B48: =B5+B6 -> 0 | C48: =C5+C6 -> 11500 | D48: =D5+D6 -> 25500 | E48: =E5+E6 -> 30500 | F48: =F5+F6 -> 58500 | G48: =G5+G6 -> 68500 | H48: =H5+H6 -> 90000 | I48: =I5+I6 -> 102500 | ... AK48: =AK5+AK6 -> 1002800
A50: Cost of Sales | B50: =B7+B8+SUM(B17:B20)*$B26 -> 64500 | C50: =C7+C8+SUM(C17:C20)*$B26 -> 93500 | D50: =D7+D8+SUM(D17:D20)*$B26 -> 98000 | E50: =E7+E8+SUM(E17:E20)*$B26 -> 107000 | F50: =F7+F8+SUM(F17:F20)*$B26 -> 136000 | G50: =G7+G8+SUM(G17:G20)*$B26 -> 140500 | H50: =H7+H8+SUM(H17:H20)*$B26 -> 145000 | I50: =I7+I8+SUM(I17:I20)*$B26 -> 149500 | ... AK50: =AK7+AK8+SUM(AK17:AK20)*$B26 -> 450000
A51: AI Agents | B51: =$B28*B23 -> 110000 | C51: =$B28*C23 -> 130000 | D51: =$B28*D23 -> 130000 | E51: =$B28*E23 -> 130000 | F51: =$B28*F23 -> 150000 | G51: =$B28*G23 -> 150000 | H51: =$B28*H23 -> 160000 | I51: =$B28*I23 -> 160000 | ... AK51: =$B28*AK23 -> 370000
A52: Development | B52: =B21*$B26 -> 30000 | C52: =C21*$B26 -> 30000 | D52: =D21*$B26 -> 30000 | E52: =E21*$B26 -> 30000 | F52: =F21*$B26 -> 30000 | G52: =G21*$B26 -> 30000 | H52: =H21*$B26 -> 30000 | I52: =I21*$B26 -> 30000 | ... AK52: =AK21*$B26 -> 50000
A53: G&A | B53: =B22*$B26*(1+$B27) -> 25000 | C53: =C22*$B26*(1+$B27) -> 25000 | D53: =D22*$B26*(1+$B27) -> 25000 | E53: =E22*$B26*(1+$B27) -> 25000 | F53: =F22*$B26*(1+$B27) -> 25000 | G53: =G22*$B26*(1+$B27) -> 25000 | H53: =H22*$B26*(1+$B27) -> 37500 | I53: =I22*$B26*(1+$B27) -> 37500 | ... AK53: =AK22*$B26*(1+$B27) -> 62500
A54: Expenses | B54: =SUM(B50:B53) -> 229500 | C54: =SUM(C50:C53) -> 278500 | D54: =SUM(D50:D53) -> 283000 | E54: =SUM(E50:E53) -> 292000 | F54: =SUM(F50:F53) -> 341000 | G54: =SUM(G50:G53) -> 345500 | H54: =SUM(H50:H53) -> 372500 | I54: =SUM(I50:I53) -> 377000 | ... AK54: =SUM(AK50:AK53) -> 932500
A56: EBITDA | B56: =B48-B54 -> -229500 | C56: =C48-C54 -> -267000 | D56: =D48-D54 -> -257500 | E56: =E48-E54 -> -261500 | F56: =F48-F54 -> -282500 | G56: =G48-G54 -> -277000 | H56: =H48-H54 -> -282500 | I56: =I48-I54 -> -274500 | ... AK56: =AK48-AK54 -> 70300
A58: Cummulative Cash | B58: =B56 -> -229500 | C58: =B58+C56 -> -496500 | D58: =C58+D56 -> -754000 | E58: =D58+E56 -> -1015500 | F58: =E58+F56 -> -1298000 | G58: =F58+G56 -> -1575000 | H58: =G58+H56 -> -1857500 | I58: =H58+I56 -> -2132000 | J58: =I58+J56 -> -2407000 | ... AK58: =AJ58+AK56 -> -6130500
